ninja_keys/__init__.py
ninja_keys/admin.py
ninja_keys/apps.py
ninja_keys/auth.py
ninja_keys/crypto.py
ninja_keys/models.py
ninja_keys/py.typed
ninja_keys/utils.py
ninja_keys/validators.py
ninja_keys/migrations/0001_initial.py
ninja_keys/migrations/__init__.py
ninja_keys-1.0.1.dist-info/METADATA
ninja_keys-1.0.1.dist-info/WHEEL
ninja_keys-1.0.1.dist-info/licenses/LICENSE
ninja_keys-1.0.1.dist-info/RECORD
