Metadata-Version: 2.4
Name: ninja-keys
Version: 1.0.1
Summary: API Keys for Django Ninja
Project-URL: Homepage, https://github.com/feliperalmeida/ninja-keys
Project-URL: Documentation, https://github.com/feliperalmeida/ninja-keys
Author-email: "Felipe R. de Almeida" <felipe@security.dev>
License: MIT
License-File: LICENSE
Keywords: api,authentication,authorization,django,django-ninja,ninja,security
Classifier: Development Status :: 4 - Beta
Classifier: Environment :: Web Environment
Classifier: Framework :: Django
Classifier: Framework :: Django :: 4.2
Classifier: Framework :: Django :: 5.0
Classifier: Framework :: Django :: 5.1
Classifier: Intended Audience :: Developers
Classifier: Operating System :: OS Independent
Classifier: Programming Language :: Python :: 3 :: Only
Classifier: Programming Language :: Python :: 3.9
Classifier: Programming Language :: Python :: 3.10
Classifier: Programming Language :: Python :: 3.11
Classifier: Programming Language :: Python :: 3.12
Classifier: Programming Language :: Python :: 3.13
Classifier: Topic :: Software Development :: Libraries :: Python Modules
Requires-Python: >=3.9
